culebratester_client/__init__.py
culebratester_client/api_client.py
culebratester_client/configuration.py
culebratester_client/rest.py
culebratester_client/api/__init__.py
culebratester_client/api/default_api.py
culebratester_client/models/__init__.py
culebratester_client/models/any_value.py
culebratester_client/models/body.py
culebratester_client/models/body1.py
culebratester_client/models/boolean_response.py
culebratester_client/models/click_body.py
culebratester_client/models/culebra_info.py
culebratester_client/models/current_package_name.py
culebratester_client/models/display_height.py
culebratester_client/models/display_real_size.py
culebratester_client/models/display_rotation_enum.py
culebratester_client/models/display_rotation_response.py
culebratester_client/models/display_size_dp.py
culebratester_client/models/display_width.py
culebratester_client/models/help.py
culebratester_client/models/inline_response200.py
culebratester_client/models/inline_response2001.py
culebratester_client/models/last_traversed_text.py
culebratester_client/models/locale.py
culebratester_client/models/number_response.py
culebratester_client/models/object_ref.py
culebratester_client/models/pattern.py
culebratester_client/models/perform_two_pointer_gesture_body.py
culebratester_client/models/pixel.py
culebratester_client/models/point.py
culebratester_client/models/product_name.py
culebratester_client/models/rect.py
culebratester_client/models/selector.py
culebratester_client/models/status_response.py
culebratester_client/models/string_response.py
culebratester_client/models/swipe_body.py
culebratester_client/models/text.py
culebratester_client/models/timeout.py
culebratester_client/models/window_hierarchy.py
culebratester_client/models/window_hierarchy_child.py
test/__init__.py
test/test_any_value.py
test/test_boolean_response.py
test/test_click_body.py
test/test_culebra_info.py
test/test_current_package_name.py
test/test_default_api.py
test/test_display_height.py
culebratester_client-2.0.71.dist-info/LICENSE
culebratester_client-2.0.71.dist-info/METADATA
culebratester_client-2.0.71.dist-info/WHEEL
culebratester_client-2.0.71.dist-info/top_level.txt
culebratester_client-2.0.71.dist-info/RECORD
