Metadata-Version: 2.1
Name: culebratester-client
Version: 2.0.71
Summary: CulebraTester
Home-page: http://github.com/dtmilano/CulebraTester2-client
Author-email: 
Keywords: Swagger,CulebraTester
License-File: LICENSE
Requires-Dist: urllib3 >=1.15
Requires-Dist: six >=1.10
Requires-Dist: certifi
Requires-Dist: python-dateutil
